[
	{
	  "referencenumber": "REF001",
	  "desc": "A nearby wall shows extensive graffiti with vivid colors and bold tags. Community members hope to see a quick cleanup effort.",
	  "type": "Graffiti",
	  "postalCode": "M5A0A1",
	  "image": "https://via.placeholder.com/100",
	  "email": "user1@example.com",
	  "status": "Solved",
	  "address": "Random Address 1, Toronto, ON",
	  "latlng": {
		"lat": 43.660624,
		"lng": -79.365955
	  }
	},
	{
	  "referencenumber": "REF002",
	  "desc": "The sidewalk in this area is cracked and uneven, posing hazards for pedestrians and needing immediate repair.",
	  "type": "Broken Sidewalk",
	  "postalCode": "M4W1E6",
	  "image": "https://via.placeholder.com/100",
	  "email": "user2@example.com",
	  "status": "Pending",
	  "address": "Random Address 2, Toronto, ON",
	  "latlng": {
		"lat": 43.672032,
		"lng": -79.380928
	  }
	},
	{
	  "referencenumber": "REF003",
	  "desc": "A section of the sidewalk has large cracks and misaligned pavement pieces, making walking unsafe.",
	  "type": "Broken Sidewalk",
	  "postalCode": "M6K1J1",
	  "image": "https://via.placeholder.com/100",
	  "email": "user3@example.com",
	  "status": "Pending",
	  "address": "Random Address 3, Toronto, ON",
	  "latlng": {
		"lat": 43.637013,
		"lng": -79.438185
	  }
	},
	{
	  "referencenumber": "REF004",
	  "desc": "Residents have reported persistent late-night disturbances. Authorities are investigating the source of the noise.",
	  "type": "Noise Complaint",
	  "postalCode": "M5V3L9",
	  "image": "https://via.placeholder.com/100",
	  "email": "user4@example.com",
	  "status": "Solved",
	  "address": "Random Address 4, Toronto, ON",
	  "latlng": {
		"lat": 43.641974,
		"lng": -79.385616
	  }
	},
	{
	  "referencenumber": "REF005",
	  "desc": "A sizable pothole has formed on the roadway, posing risks to vehicles and calling for urgent repair action.",
	  "type": "Pothole",
	  "postalCode": "M4L3W6",
	  "image": "https://via.placeholder.com/100",
	  "email": "user5@example.com",
	  "status": "Solved",
	  "address": "Random Address 5, Toronto, ON",
	  "latlng": {
		"lat": 43.663229,
		"lng": -79.309024
	  }
	},
	{
	  "referencenumber": "REF006",
	  "desc": "Colorful graffiti marks cover a local wall. Although some appreciate the art, many consider it vandalism that should be removed.",
	  "type": "Graffiti",
	  "postalCode": "M6P2G6",
	  "image": "https://via.placeholder.com/100",
	  "email": "user6@example.com",
	  "status": "Pending",
	  "address": "Random Address 6, Toronto, ON",
	  "latlng": {
		"lat": 43.661665,
		"lng": -79.460035
	  }
	},
	{
	  "referencenumber": "REF007",
	  "desc": "Persistent graffiti markings detract from the neighborhood's charm. Local groups are considering community cleanup initiatives.",
	  "type": "Graffiti",
	  "postalCode": "M5R2H8",
	  "image": "https://via.placeholder.com/100",
	  "email": "user7@example.com",
	  "status": "Solved",
	  "address": "Random Address 7, Toronto, ON",
	  "latlng": {
		"lat": 43.675023,
		"lng": -79.397027
	  }
	},
	{
	  "referencenumber": "REF008",
	  "desc": "An unusually large pothole has been reported on this street, causing inconvenience to commuters and urging prompt repairs.",
	  "type": "Pothole",
	  "postalCode": "M4J1C5",
	  "image": "https://via.placeholder.com/100",
	  "email": "user8@example.com",
	  "status": "Pending",
	  "address": "Random Address 8, Toronto, ON",
	  "latlng": {
		"lat": 43.675301,
		"lng": -79.336475
	  }
	},
	{
	  "referencenumber": "REF009",
	  "desc": "A malfunctioning streetlight has left the area poorly illuminated at night, prompting safety concerns for local residents.",
	  "type": "Streetlight",
	  "postalCode": "M6G1Y8",
	  "image": "https://via.placeholder.com/100",
	  "email": "user9@example.com",
	  "status": "Pending",
	  "address": "Random Address 9, Toronto, ON",
	  "latlng": {
		"lat": 43.672222,
		"lng": -79.41785
	  }
	},
	{
	  "referencenumber": "REF010",
	  "desc": "The roadway once troubled by a deep pothole has been patched, significantly enhancing driving safety.",
	  "type": "Pothole",
	  "postalCode": "M5H2N2",
	  "image": "https://via.placeholder.com/100",
	  "email": "user10@example.com",
	  "status": "Solved",
	  "address": "Random Address 10, Toronto, ON",
	  "latlng": {
		"lat": 43.678777,
		"lng": -79.372865
	  }
	},
	{
	  "referencenumber": "REF011",
	  "desc": "A streetlight on this block is flickering and often goes dark, raising concerns for safe nighttime activity.",
	  "type": "Streetlight",
	  "postalCode": "M4C5K9",
	  "image": "https://via.placeholder.com/100",
	  "email": "user11@example.com",
	  "status": "Pending",
	  "address": "Random Address 11, Toronto, ON",
	  "latlng": {
		"lat": 43.692281,
		"lng": -79.31074
	  }
	},
	{
	  "referencenumber": "REF012",
	  "desc": "This streetlight shows inconsistent illumination, prompting concerns about dark spots in the neighborhood.",
	  "type": "Streetlight",
	  "postalCode": "M6E4A8",
	  "image": "https://via.placeholder.com/100",
	  "email": "user12@example.com",
	  "status": "Solved",
	  "address": "Random Address 12, Toronto, ON",
	  "latlng": {
		"lat": 43.679379,
		"lng": -79.448505
	  }
	},
	{
	  "referencenumber": "REF013",
	  "desc": "A broken section of the sidewalk—with a noticeable gap—creates a tripping hazard for pedestrians and needs prompt repair.",
	  "type": "Broken Sidewalk",
	  "postalCode": "M5J2Z2",
	  "image": "https://via.placeholder.com/100",
	  "email": "user13@example.com",
	  "status": "Pending",
	  "address": "Random Address 13, Toronto, ON",
	  "latlng": {
		"lat": 43.641763,
		"lng": -79.381553
	  }
	},
	{
	  "referencenumber": "REF014",
	  "desc": "Cracks and uneven slabs in this sidewalk have created a noticeable break, urging maintenance for safer pedestrian access.",
	  "type": "Broken Sidewalk",
	  "postalCode": "M4X1K2",
	  "image": "https://via.placeholder.com/100",
	  "email": "user14@example.com",
	  "status": "Pending",
	  "address": "Random Address 14, Toronto, ON",
	  "latlng": {
		"lat": 43.665441,
		"lng": -79.374373
	  }
	},
	{
	  "referencenumber": "REF015",
	  "desc": "A deep pothole on the roadway has raised concerns about potential vehicle damage, highlighting the need for urgent repair.",
	  "type": "Pothole",
	  "postalCode": "M6R1Z9",
	  "image": "https://via.placeholder.com/100",
	  "email": "user15@example.com",
	  "status": "Solved",
	  "address": "Random Address 15, Toronto, ON",
	  "latlng": {
		"lat": 43.654138,
		"lng": -79.457502
	  }
	},
	{
	  "referencenumber": "REF016",
	  "desc": "Weathered pavement and dislodged bricks have left this section of the sidewalk broken, posing difficulty for pedestrians.",
	  "type": "Broken Sidewalk",
	  "postalCode": "M5T3A7",
	  "image": "https://via.placeholder.com/100",
	  "email": "user16@example.com",
	  "status": "Solved",
	  "address": "Random Address 16, Toronto, ON",
	  "latlng": {
		"lat": 43.65615,
		"lng": -79.390049
	  }
	},
	{
	  "referencenumber": "REF017",
	  "desc": "Local reports indicate that a streetlight is completely out, leaving an area unlit and potentially hazardous at night.",
	  "type": "Streetlight",
	  "postalCode": "M4E2B5",
	  "image": "https://via.placeholder.com/100",
	  "email": "user17@example.com",
	  "status": "Pending",
	  "address": "Random Address 17, Toronto, ON",
	  "latlng": {
		"lat": 43.682247,
		"lng": -79.308307
	  }
	},
	{
	  "referencenumber": "REF018",
	  "desc": "A rugged pothole has been identified on this busy road, posing a threat to motorists if not promptly attended to.",
	  "type": "Pothole",
	  "postalCode": "M6H4E2",
	  "image": "https://via.placeholder.com/100",
	  "email": "user18@example.com",
	  "status": "Solved",
	  "address": "Random Address 18, Toronto, ON",
	  "latlng": {
		"lat": 43.653226,
		"lng": -79.383184
	  }
	},
	{
	  "referencenumber": "REF019",
	  "desc": "A series of noise disturbances has been reported, prompting investigations into possible sources of excessive sound in the area.",
	  "type": "Noise Complaint",
	  "postalCode": "M5S2C6",
	  "image": "https://via.placeholder.com/100",
	  "email": "user19@example.com",
	  "status": "Pending",
	  "address": "Random Address 19, Toronto, ON",
	  "latlng": {
		"lat": 43.667798,
		"lng": -79.394213
	  }
	},
	{
	  "referencenumber": "REF020",
	  "desc": "A streetlight along this route recently malfunctioned, leaving the area dim and prompting quick remedial measures.",
	  "type": "Streetlight",
	  "postalCode": "M4N3M5",
	  "image": "https://via.placeholder.com/100",
	  "email": "user20@example.com",
	  "status": "Solved",
	  "address": "Random Address 20, Toronto, ON",
	  "latlng": {
		"lat": 43.721793,
		"lng": -79.376264
	  }
	}
  ]
  